<?xml version="1.0" ?>
<IV_Curves>
    <Version>1.00</Version>
    <Curve>
        <Name>B1</Name>
        <GUID>82bef30b-03f6-4d79-9187-aba3b2044954</GUID>
        <Category>Unfiled</Category>
        <Site></Site>
        <Sub_System></Sub_System>
        <ModuleID>111</ModuleID>
        <Misc></Misc>
        <Notes></Notes>
        <NormData></NormData>
        <PeakPower units="Watts">1.110763</PeakPower>
        <Vpeak units="Volts">4.098056</Vpeak>
        <Ipeak units="Amps">0.271046</Ipeak>
        <Voc units="Volts">4.681171</Voc>
        <Voltage_Range units="Volts">5.281953</Voltage_Range>
        <Voltage_Resolution units="Volts/Bit">0.000161197</Voltage_Resolution>
        <Isc units="Amps">0.278266</Isc>
        <Current_Range units="Amps">1.991250</Current_Range>
        <Current_Resolution units="Amps/Bit">6.077e-05</Current_Resolution>
        <FillFactor units="%">85.272121</FillFactor>
        <Date_Time date="05/08/2021" time="21:50:08">2021-05-08T21:50:08</Date_Time>
        <AmpRange>High</AmpRange>
        <NormSourceGUID>00000000-0000-0000-0000-000000000000</NormSourceGUID>
        <Normalized>false</Normalized>
        <Temp1 tc_type="T">
            <Value units="C">23.360186</Value>
            <InputSource>THERMOCOUPLE</InputSource>
        </Temp1>
        <Irradiances />
        <Temperatures>
            <Temperature value="2.336019E+01" description="T_B1" type="THERMOCOUPLE" units="C" tc_type="T" data_source="0" input_id="34" index="0" />
        </Temperatures>
        <AuxInputs />
        <AfterIrradiances />
        <AfterTemperatures>
            <Temperature value="2.336019E+01" description="T_B1" type="THERMOCOUPLE" units="C" tc_type="T" data_source="0" input_id="34" index="0" />
        </AfterTemperatures>
        <AfterAuxInputs />
        <Points>
            <Point>
                <Volts>0.000000</Volts>
                <Amps>0.278266</Amps>
            </Point>
            <Point>
                <Volts>0.021762</Volts>
                <Amps>0.278266</Amps>
            </Point>
            <Point>
                <Volts>0.021633</Volts>
                <Amps>0.278399</Amps>
            </Point>
            <Point>
                <Volts>0.060965</Volts>
                <Amps>0.278886</Amps>
            </Point>
            <Point>
                <Volts>0.087047</Volts>
                <Amps>0.278825</Amps>
            </Point>
            <Point>
                <Volts>0.113547</Volts>
                <Amps>0.278290</Amps>
            </Point>
            <Point>
                <Volts>0.139823</Volts>
                <Amps>0.278886</Amps>
            </Point>
            <Point>
                <Volts>0.165953</Volts>
                <Amps>0.278311</Amps>
            </Point>
            <Point>
                <Volts>0.192147</Volts>
                <Amps>0.278521</Amps>
            </Point>
            <Point>
                <Volts>0.218680</Volts>
                <Amps>0.279250</Amps>
            </Point>
            <Point>
                <Volts>0.244794</Volts>
                <Amps>0.278314</Amps>
            </Point>
            <Point>
                <Volts>0.271037</Volts>
                <Amps>0.278740</Amps>
            </Point>
            <Point>
                <Volts>0.297054</Volts>
                <Amps>0.278314</Amps>
            </Point>
            <Point>
                <Volts>0.323297</Volts>
                <Amps>0.278254</Amps>
            </Point>
            <Point>
                <Volts>0.349347</Volts>
                <Amps>0.278764</Amps>
            </Point>
            <Point>
                <Volts>0.375654</Volts>
                <Amps>0.278533</Amps>
            </Point>
            <Point>
                <Volts>0.401897</Volts>
                <Amps>0.278813</Amps>
            </Point>
            <Point>
                <Volts>0.428011</Volts>
                <Amps>0.278995</Amps>
            </Point>
            <Point>
                <Volts>0.454415</Volts>
                <Amps>0.278776</Amps>
            </Point>
            <Point>
                <Volts>0.480626</Volts>
                <Amps>0.278436</Amps>
            </Point>
            <Point>
                <Volts>0.506708</Volts>
                <Amps>0.278314</Amps>
            </Point>
            <Point>
                <Volts>0.532886</Volts>
                <Amps>0.278946</Amps>
            </Point>
            <Point>
                <Volts>0.559032</Volts>
                <Amps>0.278740</Amps>
            </Point>
            <Point>
                <Volts>0.585308</Volts>
                <Amps>0.278472</Amps>
            </Point>
            <Point>
                <Volts>0.611293</Volts>
                <Amps>0.278800</Amps>
            </Point>
            <Point>
                <Volts>0.637600</Volts>
                <Amps>0.278460</Amps>
            </Point>
            <Point>
                <Volts>0.663907</Volts>
                <Amps>0.278314</Amps>
            </Point>
            <Point>
                <Volts>0.690279</Volts>
                <Amps>0.278752</Amps>
            </Point>
            <Point>
                <Volts>0.716393</Volts>
                <Amps>0.278691</Amps>
            </Point>
            <Point>
                <Volts>0.742668</Volts>
                <Amps>0.278375</Amps>
            </Point>
            <Point>
                <Volts>0.768782</Volts>
                <Amps>0.278302</Amps>
            </Point>
            <Point>
                <Volts>0.795187</Volts>
                <Amps>0.278898</Amps>
            </Point>
            <Point>
                <Volts>0.821397</Volts>
                <Amps>0.278436</Amps>
            </Point>
            <Point>
                <Volts>0.847543</Volts>
                <Amps>0.279068</Amps>
            </Point>
            <Point>
                <Volts>0.873593</Volts>
                <Amps>0.278497</Amps>
            </Point>
            <Point>
                <Volts>0.899965</Volts>
                <Amps>0.279129</Amps>
            </Point>
            <Point>
                <Volts>0.926111</Volts>
                <Amps>0.278655</Amps>
            </Point>
            <Point>
                <Volts>0.952193</Volts>
                <Amps>0.278886</Amps>
            </Point>
            <Point>
                <Volts>0.978468</Volts>
                <Amps>0.278691</Amps>
            </Point>
            <Point>
                <Volts>1.004646</Volts>
                <Amps>0.278010</Amps>
            </Point>
            <Point>
                <Volts>1.030728</Volts>
                <Amps>0.278752</Amps>
            </Point>
            <Point>
                <Volts>1.057068</Volts>
                <Amps>0.278995</Amps>
            </Point>
            <Point>
                <Volts>1.083311</Volts>
                <Amps>0.278484</Amps>
            </Point>
            <Point>
                <Volts>1.109489</Volts>
                <Amps>0.278606</Amps>
            </Point>
            <Point>
                <Volts>1.135796</Volts>
                <Amps>0.279116</Amps>
            </Point>
            <Point>
                <Volts>1.161975</Volts>
                <Amps>0.278144</Amps>
            </Point>
            <Point>
                <Volts>1.188315</Volts>
                <Amps>0.278217</Amps>
            </Point>
            <Point>
                <Volts>1.214396</Volts>
                <Amps>0.278108</Amps>
            </Point>
            <Point>
                <Volts>1.240639</Volts>
                <Amps>0.278752</Amps>
            </Point>
            <Point>
                <Volts>1.266785</Volts>
                <Amps>0.278703</Amps>
            </Point>
            <Point>
                <Volts>1.293286</Volts>
                <Amps>0.278691</Amps>
            </Point>
            <Point>
                <Volts>1.319465</Volts>
                <Amps>0.278618</Amps>
            </Point>
            <Point>
                <Volts>1.345643</Volts>
                <Amps>0.278570</Amps>
            </Point>
            <Point>
                <Volts>1.371789</Volts>
                <Amps>0.278946</Amps>
            </Point>
            <Point>
                <Volts>1.398161</Volts>
                <Amps>0.278083</Amps>
            </Point>
            <Point>
                <Volts>1.424243</Volts>
                <Amps>0.278570</Amps>
            </Point>
            <Point>
                <Volts>1.450421</Volts>
                <Amps>0.278594</Amps>
            </Point>
            <Point>
                <Volts>1.476761</Volts>
                <Amps>0.279068</Amps>
            </Point>
            <Point>
                <Volts>1.502940</Volts>
                <Amps>0.278509</Amps>
            </Point>
            <Point>
                <Volts>1.529021</Volts>
                <Amps>0.278278</Amps>
            </Point>
            <Point>
                <Volts>1.555458</Volts>
                <Amps>0.278424</Amps>
            </Point>
            <Point>
                <Volts>1.581572</Volts>
                <Amps>0.278545</Amps>
            </Point>
            <Point>
                <Volts>1.607814</Volts>
                <Amps>0.277816</Amps>
            </Point>
            <Point>
                <Volts>1.634315</Volts>
                <Amps>0.277865</Amps>
            </Point>
            <Point>
                <Volts>1.660429</Volts>
                <Amps>0.279056</Amps>
            </Point>
            <Point>
                <Volts>1.686608</Volts>
                <Amps>0.277877</Amps>
            </Point>
            <Point>
                <Volts>1.712689</Volts>
                <Amps>0.278679</Amps>
            </Point>
            <Point>
                <Volts>1.738932</Volts>
                <Amps>0.278229</Amps>
            </Point>
            <Point>
                <Volts>1.765304</Volts>
                <Amps>0.278375</Amps>
            </Point>
            <Point>
                <Volts>1.791483</Volts>
                <Amps>0.278691</Amps>
            </Point>
            <Point>
                <Volts>1.817564</Volts>
                <Amps>0.278934</Amps>
            </Point>
            <Point>
                <Volts>1.843743</Volts>
                <Amps>0.278096</Amps>
            </Point>
            <Point>
                <Volts>1.870050</Volts>
                <Amps>0.278667</Amps>
            </Point>
            <Point>
                <Volts>1.896358</Volts>
                <Amps>0.278873</Amps>
            </Point>
            <Point>
                <Volts>1.922472</Volts>
                <Amps>0.278229</Amps>
            </Point>
            <Point>
                <Volts>1.948521</Volts>
                <Amps>0.278181</Amps>
            </Point>
            <Point>
                <Volts>1.974957</Volts>
                <Amps>0.278594</Amps>
            </Point>
            <Point>
                <Volts>2.001233</Volts>
                <Amps>0.278484</Amps>
            </Point>
            <Point>
                <Volts>2.027347</Volts>
                <Amps>0.278229</Amps>
            </Point>
            <Point>
                <Volts>2.053622</Volts>
                <Amps>0.278387</Amps>
            </Point>
            <Point>
                <Volts>2.079833</Volts>
                <Amps>0.278059</Amps>
            </Point>
            <Point>
                <Volts>2.106108</Volts>
                <Amps>0.277804</Amps>
            </Point>
            <Point>
                <Volts>2.132254</Volts>
                <Amps>0.278472</Amps>
            </Point>
            <Point>
                <Volts>2.158464</Volts>
                <Amps>0.278229</Amps>
            </Point>
            <Point>
                <Volts>2.184643</Volts>
                <Amps>0.278606</Amps>
            </Point>
            <Point>
                <Volts>2.210854</Volts>
                <Amps>0.278618</Amps>
            </Point>
            <Point>
                <Volts>2.237064</Volts>
                <Amps>0.278375</Amps>
            </Point>
            <Point>
                <Volts>2.263243</Volts>
                <Amps>0.277889</Amps>
            </Point>
            <Point>
                <Volts>2.289454</Volts>
                <Amps>0.278898</Amps>
            </Point>
            <Point>
                <Volts>2.315697</Volts>
                <Amps>0.278703</Amps>
            </Point>
            <Point>
                <Volts>2.341778</Volts>
                <Amps>0.279116</Amps>
            </Point>
            <Point>
                <Volts>2.368150</Volts>
                <Amps>0.278120</Amps>
            </Point>
            <Point>
                <Volts>2.394361</Volts>
                <Amps>0.278691</Amps>
            </Point>
            <Point>
                <Volts>2.420572</Volts>
                <Amps>0.278205</Amps>
            </Point>
            <Point>
                <Volts>2.446750</Volts>
                <Amps>0.278448</Amps>
            </Point>
            <Point>
                <Volts>2.472928</Volts>
                <Amps>0.278120</Amps>
            </Point>
            <Point>
                <Volts>2.499042</Volts>
                <Amps>0.277950</Amps>
            </Point>
            <Point>
                <Volts>2.525358</Volts>
                <Amps>0.278539</Amps>
            </Point>
            <Point>
                <Volts>2.551754</Volts>
                <Amps>0.278035</Amps>
            </Point>
            <Point>
                <Volts>2.577707</Volts>
                <Amps>0.278108</Amps>
            </Point>
            <Point>
                <Volts>2.604014</Volts>
                <Amps>0.278570</Amps>
            </Point>
            <Point>
                <Volts>2.630321</Volts>
                <Amps>0.277950</Amps>
            </Point>
            <Point>
                <Volts>2.656532</Volts>
                <Amps>0.277220</Amps>
            </Point>
            <Point>
                <Volts>2.682710</Volts>
                <Amps>0.278472</Amps>
            </Point>
            <Point>
                <Volts>2.708986</Volts>
                <Amps>0.278752</Amps>
            </Point>
            <Point>
                <Volts>2.735100</Volts>
                <Amps>0.278387</Amps>
            </Point>
            <Point>
                <Volts>2.761440</Volts>
                <Amps>0.277488</Amps>
            </Point>
            <Point>
                <Volts>2.787650</Volts>
                <Amps>0.277318</Amps>
            </Point>
            <Point>
                <Volts>2.813893</Volts>
                <Amps>0.277743</Amps>
            </Point>
            <Point>
                <Volts>2.840200</Volts>
                <Amps>0.277573</Amps>
            </Point>
            <Point>
                <Volts>2.866186</Volts>
                <Amps>0.276856</Amps>
            </Point>
            <Point>
                <Volts>2.892428</Volts>
                <Amps>0.277269</Amps>
            </Point>
            <Point>
                <Volts>2.918800</Volts>
                <Amps>0.276990</Amps>
            </Point>
            <Point>
                <Volts>2.945107</Volts>
                <Amps>0.277366</Amps>
            </Point>
            <Point>
                <Volts>2.971641</Volts>
                <Amps>0.277439</Amps>
            </Point>
            <Point>
                <Volts>2.997561</Volts>
                <Amps>0.277439</Amps>
            </Point>
            <Point>
                <Volts>3.023804</Volts>
                <Amps>0.277148</Amps>
            </Point>
            <Point>
                <Volts>3.050144</Volts>
                <Amps>0.277536</Amps>
            </Point>
            <Point>
                <Volts>3.076258</Volts>
                <Amps>0.277378</Amps>
            </Point>
            <Point>
                <Volts>3.102307</Volts>
                <Amps>0.277464</Amps>
            </Point>
            <Point>
                <Volts>3.128711</Volts>
                <Amps>0.277135</Amps>
            </Point>
            <Point>
                <Volts>3.154857</Volts>
                <Amps>0.277342</Amps>
            </Point>
            <Point>
                <Volts>3.181165</Volts>
                <Amps>0.277354</Amps>
            </Point>
            <Point>
                <Volts>3.207376</Volts>
                <Amps>0.277549</Amps>
            </Point>
            <Point>
                <Volts>3.233425</Volts>
                <Amps>0.277172</Amps>
            </Point>
            <Point>
                <Volts>3.259797</Volts>
                <Amps>0.278120</Amps>
            </Point>
            <Point>
                <Volts>3.285943</Volts>
                <Amps>0.277512</Amps>
            </Point>
            <Point>
                <Volts>3.312379</Volts>
                <Amps>0.277038</Amps>
            </Point>
            <Point>
                <Volts>3.338518</Volts>
                <Amps>0.276777</Amps>
            </Point>
            <Point>
                <Volts>3.364769</Volts>
                <Amps>0.276904</Amps>
            </Point>
            <Point>
                <Volts>3.390947</Volts>
                <Amps>0.277123</Amps>
            </Point>
            <Point>
                <Volts>3.417093</Volts>
                <Amps>0.277075</Amps>
            </Point>
            <Point>
                <Volts>3.443143</Volts>
                <Amps>0.277464</Amps>
            </Point>
            <Point>
                <Volts>3.469482</Volts>
                <Amps>0.277135</Amps>
            </Point>
            <Point>
                <Volts>3.495693</Volts>
                <Amps>0.276917</Amps>
            </Point>
            <Point>
                <Volts>3.522033</Volts>
                <Amps>0.276661</Amps>
            </Point>
            <Point>
                <Volts>3.548340</Volts>
                <Amps>0.277002</Amps>
            </Point>
            <Point>
                <Volts>3.574358</Volts>
                <Amps>0.277014</Amps>
            </Point>
            <Point>
                <Volts>3.600471</Volts>
                <Amps>0.277585</Amps>
            </Point>
            <Point>
                <Volts>3.626682</Volts>
                <Amps>0.276880</Amps>
            </Point>
            <Point>
                <Volts>3.652796</Volts>
                <Amps>0.276783</Amps>
            </Point>
            <Point>
                <Volts>3.678975</Volts>
                <Amps>0.276260</Amps>
            </Point>
            <Point>
                <Volts>3.705185</Volts>
                <Amps>0.276698</Amps>
            </Point>
            <Point>
                <Volts>3.731622</Volts>
                <Amps>0.275750</Amps>
            </Point>
            <Point>
                <Volts>3.757703</Volts>
                <Amps>0.276977</Amps>
            </Point>
            <Point>
                <Volts>3.783882</Volts>
                <Amps>0.276321</Amps>
            </Point>
            <Point>
                <Volts>3.810060</Volts>
                <Amps>0.276151</Amps>
            </Point>
            <Point>
                <Volts>3.836206</Volts>
                <Amps>0.275750</Amps>
            </Point>
            <Point>
                <Volts>3.862514</Volts>
                <Amps>0.276333</Amps>
            </Point>
            <Point>
                <Volts>3.888725</Volts>
                <Amps>0.275713</Amps>
            </Point>
            <Point>
                <Volts>3.915129</Volts>
                <Amps>0.276139</Amps>
            </Point>
            <Point>
                <Volts>3.941275</Volts>
                <Amps>0.275774</Amps>
            </Point>
            <Point>
                <Volts>3.967163</Volts>
                <Amps>0.275604</Amps>
            </Point>
            <Point>
                <Volts>3.993664</Volts>
                <Amps>0.275094</Amps>
            </Point>
            <Point>
                <Volts>4.019843</Volts>
                <Amps>0.273623</Amps>
            </Point>
            <Point>
                <Volts>4.045763</Volts>
                <Amps>0.273149</Amps>
            </Point>
            <Point>
                <Volts>4.072038</Volts>
                <Amps>0.272201</Amps>
            </Point>
            <Point>
                <Volts>4.098056</Volts>
                <Amps>0.271046</Amps>
            </Point>
            <Point>
                <Volts>4.124234</Volts>
                <Amps>0.268919</Amps>
            </Point>
            <Point>
                <Volts>4.150428</Volts>
                <Amps>0.266492</Amps>
            </Point>
            <Point>
                <Volts>4.176300</Volts>
                <Amps>0.264981</Amps>
            </Point>
            <Point>
                <Volts>4.202350</Volts>
                <Amps>0.262089</Amps>
            </Point>
            <Point>
                <Volts>4.228368</Volts>
                <Amps>0.258576</Amps>
            </Point>
            <Point>
                <Volts>4.254256</Volts>
                <Amps>0.254274</Amps>
            </Point>
            <Point>
                <Volts>4.280241</Volts>
                <Amps>0.249412</Amps>
            </Point>
            <Point>
                <Volts>4.306161</Volts>
                <Amps>0.243493</Amps>
            </Point>
            <Point>
                <Volts>4.332211</Volts>
                <Amps>0.238121</Amps>
            </Point>
            <Point>
                <Volts>4.357616</Volts>
                <Amps>0.230209</Amps>
            </Point>
            <Point>
                <Volts>4.383181</Volts>
                <Amps>0.221762</Amps>
            </Point>
            <Point>
                <Volts>4.408941</Volts>
                <Amps>0.213570</Amps>
            </Point>
            <Point>
                <Volts>4.434378</Volts>
                <Amps>0.201866</Amps>
            </Point>
            <Point>
                <Volts>4.459718</Volts>
                <Amps>0.190028</Amps>
            </Point>
            <Point>
                <Volts>4.485026</Volts>
                <Amps>0.176877</Amps>
            </Point>
            <Point>
                <Volts>4.510011</Volts>
                <Amps>0.162268</Amps>
            </Point>
            <Point>
                <Volts>4.535287</Volts>
                <Amps>0.144560</Amps>
            </Point>
            <Point>
                <Volts>4.560144</Volts>
                <Amps>0.126073</Amps>
            </Point>
            <Point>
                <Volts>4.584807</Volts>
                <Amps>0.105023</Amps>
            </Point>
            <Point>
                <Volts>4.609599</Volts>
                <Amps>0.082428</Amps>
            </Point>
            <Point>
                <Volts>4.634004</Volts>
                <Amps>0.056954</Amps>
            </Point>
            <Point>
                <Volts>4.658088</Volts>
                <Amps>0.028598</Amps>
            </Point>
            <Point>
                <Volts>4.680365</Volts>
                <Amps>0.000377</Amps>
            </Point>
            <Point>
                <Volts>4.681139</Volts>
                <Amps>-0.000085</Amps>
            </Point>
            <Point>
                <Volts>4.681171</Volts>
                <Amps>0.000000</Amps>
            </Point>
        </Points>
    </Curve>
</IV_Curves>
