<?xml version="1.0" ?>
<IV_Curves>
    <Version>1.00</Version>
    <Curve>
        <Name>M5</Name>
        <GUID>65b16f27-3b20-427e-9531-206892623372</GUID>
        <Category>Unfiled</Category>
        <Site></Site>
        <Sub_System></Sub_System>
        <ModuleID>215</ModuleID>
        <Misc></Misc>
        <Notes></Notes>
        <NormData></NormData>
        <PeakPower units="Watts">154.581848</PeakPower>
        <Vpeak units="Volts">38.185812</Vpeak>
        <Ipeak units="Amps">4.048149</Ipeak>
        <Voc units="Volts">44.536425</Voc>
        <Voltage_Range units="Volts">107.651597</Voltage_Range>
        <Voltage_Resolution units="Volts/Bit">0.00328537</Voltage_Resolution>
        <Isc units="Amps">4.183783</Isc>
        <Current_Range units="Amps">19.894067</Current_Range>
        <Current_Resolution units="Amps/Bit">0.000607137</Current_Resolution>
        <FillFactor units="%">82.961002</FillFactor>
        <Date_Time date="05/08/2021" time="15:25:28">2021-05-08T15:25:28</Date_Time>
        <AmpRange>High</AmpRange>
        <NormSourceGUID>00000000-0000-0000-0000-000000000000</NormSourceGUID>
        <Normalized>false</Normalized>
        <Irradiances />
        <Temperatures />
        <AuxInputs />
        <AfterIrradiances />
        <AfterTemperatures />
        <AfterAuxInputs />
        <Points>
            <Point>
                <Volts>0.000000</Volts>
                <Amps>4.183783</Amps>
            </Point>
            <Point>
                <Volts>1.754386</Volts>
                <Amps>4.183783</Amps>
            </Point>
            <Point>
                <Volts>1.755700</Volts>
                <Amps>4.186212</Amps>
            </Point>
            <Point>
                <Volts>2.223536</Volts>
                <Amps>4.184512</Amps>
            </Point>
            <Point>
                <Volts>2.468624</Volts>
                <Amps>4.183904</Amps>
            </Point>
            <Point>
                <Volts>2.716341</Volts>
                <Amps>4.182447</Amps>
            </Point>
            <Point>
                <Volts>2.969314</Volts>
                <Amps>4.182569</Amps>
            </Point>
            <Point>
                <Volts>3.210460</Volts>
                <Amps>4.183176</Amps>
            </Point>
            <Point>
                <Volts>3.458834</Volts>
                <Amps>4.181597</Amps>
            </Point>
            <Point>
                <Volts>3.702608</Volts>
                <Amps>4.180019</Amps>
            </Point>
            <Point>
                <Volts>3.950982</Volts>
                <Amps>4.180261</Amps>
            </Point>
            <Point>
                <Volts>4.197384</Volts>
                <Amps>4.180504</Amps>
            </Point>
            <Point>
                <Volts>4.443129</Volts>
                <Amps>4.178926</Amps>
            </Point>
            <Point>
                <Volts>4.689860</Volts>
                <Amps>4.177257</Amps>
            </Point>
            <Point>
                <Volts>4.938563</Volts>
                <Amps>4.178926</Amps>
            </Point>
            <Point>
                <Volts>5.183651</Volts>
                <Amps>4.178683</Amps>
            </Point>
            <Point>
                <Volts>5.428739</Volts>
                <Amps>4.177226</Amps>
            </Point>
            <Point>
                <Volts>5.673828</Volts>
                <Amps>4.176862</Amps>
            </Point>
            <Point>
                <Volts>5.922858</Volts>
                <Amps>4.176133</Amps>
            </Point>
            <Point>
                <Volts>6.169260</Volts>
                <Amps>4.175526</Amps>
            </Point>
            <Point>
                <Volts>6.418291</Volts>
                <Amps>4.175162</Amps>
            </Point>
            <Point>
                <Volts>6.663380</Volts>
                <Amps>4.174676</Amps>
            </Point>
            <Point>
                <Volts>6.913068</Volts>
                <Amps>4.174191</Amps>
            </Point>
            <Point>
                <Volts>7.153556</Volts>
                <Amps>4.174919</Amps>
            </Point>
            <Point>
                <Volts>7.398645</Volts>
                <Amps>4.173947</Amps>
            </Point>
            <Point>
                <Volts>7.643733</Volts>
                <Amps>4.173462</Amps>
            </Point>
            <Point>
                <Volts>7.895392</Volts>
                <Amps>4.173340</Amps>
            </Point>
            <Point>
                <Volts>8.141795</Volts>
                <Amps>4.173340</Amps>
            </Point>
            <Point>
                <Volts>8.384254</Volts>
                <Amps>4.171883</Amps>
            </Point>
            <Point>
                <Volts>8.637228</Volts>
                <Amps>4.172126</Amps>
            </Point>
            <Point>
                <Volts>8.884287</Volts>
                <Amps>4.172733</Amps>
            </Point>
            <Point>
                <Volts>9.129376</Volts>
                <Amps>4.172612</Amps>
            </Point>
            <Point>
                <Volts>9.375121</Volts>
                <Amps>4.171276</Amps>
            </Point>
            <Point>
                <Volts>9.620210</Volts>
                <Amps>4.171883</Amps>
            </Point>
            <Point>
                <Volts>9.870554</Volts>
                <Amps>4.171519</Amps>
            </Point>
            <Point>
                <Volts>10.112357</Volts>
                <Amps>4.170061</Amps>
            </Point>
            <Point>
                <Volts>10.360075</Volts>
                <Amps>4.169090</Amps>
            </Point>
            <Point>
                <Volts>10.606477</Volts>
                <Amps>4.169698</Amps>
            </Point>
            <Point>
                <Volts>10.857478</Volts>
                <Amps>4.169819</Amps>
            </Point>
            <Point>
                <Volts>11.097967</Volts>
                <Amps>4.168848</Amps>
            </Point>
            <Point>
                <Volts>11.343713</Volts>
                <Amps>4.169212</Amps>
            </Point>
            <Point>
                <Volts>11.593236</Volts>
                <Amps>4.167694</Amps>
            </Point>
            <Point>
                <Volts>11.837174</Volts>
                <Amps>4.167269</Amps>
            </Point>
            <Point>
                <Volts>12.076350</Volts>
                <Amps>4.153183</Amps>
            </Point>
            <Point>
                <Volts>12.307639</Volts>
                <Amps>4.107891</Amps>
            </Point>
            <Point>
                <Volts>12.554041</Volts>
                <Amps>4.099148</Amps>
            </Point>
            <Point>
                <Volts>12.798473</Volts>
                <Amps>4.096598</Amps>
            </Point>
            <Point>
                <Volts>13.042905</Volts>
                <Amps>4.096598</Amps>
            </Point>
            <Point>
                <Volts>13.287335</Volts>
                <Amps>4.094898</Amps>
            </Point>
            <Point>
                <Volts>13.535709</Volts>
                <Amps>4.094534</Amps>
            </Point>
            <Point>
                <Volts>13.785396</Volts>
                <Amps>4.095020</Amps>
            </Point>
            <Point>
                <Volts>14.026543</Volts>
                <Amps>4.093805</Amps>
            </Point>
            <Point>
                <Volts>14.278203</Volts>
                <Amps>4.093076</Amps>
            </Point>
            <Point>
                <Volts>14.523289</Volts>
                <Amps>4.092955</Amps>
            </Point>
            <Point>
                <Volts>14.772321</Volts>
                <Amps>4.092713</Amps>
            </Point>
            <Point>
                <Volts>15.013467</Volts>
                <Amps>4.091619</Amps>
            </Point>
            <Point>
                <Volts>15.259212</Volts>
                <Amps>4.090891</Amps>
            </Point>
            <Point>
                <Volts>15.506271</Volts>
                <Amps>4.091619</Amps>
            </Point>
            <Point>
                <Volts>15.750703</Volts>
                <Amps>4.090284</Amps>
            </Point>
            <Point>
                <Volts>15.998419</Volts>
                <Amps>4.090041</Amps>
            </Point>
            <Point>
                <Volts>16.250078</Volts>
                <Amps>4.088827</Amps>
            </Point>
            <Point>
                <Volts>16.491882</Volts>
                <Amps>4.088462</Amps>
            </Point>
            <Point>
                <Volts>16.739598</Volts>
                <Amps>4.088341</Amps>
            </Point>
            <Point>
                <Volts>16.980745</Volts>
                <Amps>4.086884</Amps>
            </Point>
            <Point>
                <Volts>17.226489</Volts>
                <Amps>4.087006</Amps>
            </Point>
            <Point>
                <Volts>17.474207</Volts>
                <Amps>4.085791</Amps>
            </Point>
            <Point>
                <Volts>17.720609</Volts>
                <Amps>4.085184</Amps>
            </Point>
            <Point>
                <Volts>17.968982</Volts>
                <Amps>4.084698</Amps>
            </Point>
            <Point>
                <Volts>18.218671</Volts>
                <Amps>4.084334</Amps>
            </Point>
            <Point>
                <Volts>18.464579</Volts>
                <Amps>4.083909</Amps>
            </Point>
            <Point>
                <Volts>18.704247</Volts>
                <Amps>4.082391</Amps>
            </Point>
            <Point>
                <Volts>18.946707</Volts>
                <Amps>4.082148</Amps>
            </Point>
            <Point>
                <Volts>19.200995</Volts>
                <Amps>4.082756</Amps>
            </Point>
            <Point>
                <Volts>19.443454</Volts>
                <Amps>4.081906</Amps>
            </Point>
            <Point>
                <Volts>19.693143</Volts>
                <Amps>4.081784</Amps>
            </Point>
            <Point>
                <Volts>19.942830</Volts>
                <Amps>4.080934</Amps>
            </Point>
            <Point>
                <Volts>20.188576</Volts>
                <Amps>4.080084</Amps>
            </Point>
            <Point>
                <Volts>20.432350</Volts>
                <Amps>4.080326</Amps>
            </Point>
            <Point>
                <Volts>20.676781</Volts>
                <Amps>4.079112</Amps>
            </Point>
            <Point>
                <Volts>20.927783</Volts>
                <Amps>4.080327</Amps>
            </Point>
            <Point>
                <Volts>21.173529</Volts>
                <Amps>4.079113</Amps>
            </Point>
            <Point>
                <Volts>21.414674</Volts>
                <Amps>4.078141</Amps>
            </Point>
            <Point>
                <Volts>21.665021</Volts>
                <Amps>4.077048</Amps>
            </Point>
            <Point>
                <Volts>21.912735</Volts>
                <Amps>4.078384</Amps>
            </Point>
            <Point>
                <Volts>22.155197</Volts>
                <Amps>4.078384</Amps>
            </Point>
            <Point>
                <Volts>22.402255</Volts>
                <Amps>4.077291</Amps>
            </Point>
            <Point>
                <Volts>22.649973</Volts>
                <Amps>4.078384</Amps>
            </Point>
            <Point>
                <Volts>22.894403</Volts>
                <Amps>4.076684</Amps>
            </Point>
            <Point>
                <Volts>23.144748</Volts>
                <Amps>4.076684</Amps>
            </Point>
            <Point>
                <Volts>23.388522</Volts>
                <Amps>4.075713</Amps>
            </Point>
            <Point>
                <Volts>23.638211</Volts>
                <Amps>4.076684</Amps>
            </Point>
            <Point>
                <Volts>23.885269</Volts>
                <Amps>4.076199</Amps>
            </Point>
            <Point>
                <Volts>24.125101</Volts>
                <Amps>4.075348</Amps>
            </Point>
            <Point>
                <Volts>24.379388</Volts>
                <Amps>4.075956</Amps>
            </Point>
            <Point>
                <Volts>24.623820</Volts>
                <Amps>4.074741</Amps>
            </Point>
            <Point>
                <Volts>24.870222</Volts>
                <Amps>4.074498</Amps>
            </Point>
            <Point>
                <Volts>25.117282</Volts>
                <Amps>4.074377</Amps>
            </Point>
            <Point>
                <Volts>25.364342</Volts>
                <Amps>4.072434</Amps>
            </Point>
            <Point>
                <Volts>25.608115</Volts>
                <Amps>4.069520</Amps>
            </Point>
            <Point>
                <Volts>25.855832</Volts>
                <Amps>4.069155</Amps>
            </Point>
            <Point>
                <Volts>26.109464</Volts>
                <Amps>4.068549</Amps>
            </Point>
            <Point>
                <Volts>26.355865</Volts>
                <Amps>4.070127</Amps>
            </Point>
            <Point>
                <Volts>26.598325</Volts>
                <Amps>4.069277</Amps>
            </Point>
            <Point>
                <Volts>26.842099</Volts>
                <Amps>4.068427</Amps>
            </Point>
            <Point>
                <Volts>27.091788</Volts>
                <Amps>4.068184</Amps>
            </Point>
            <Point>
                <Volts>27.333591</Volts>
                <Amps>4.068427</Amps>
            </Point>
            <Point>
                <Volts>27.582620</Volts>
                <Amps>4.067456</Amps>
            </Point>
            <Point>
                <Volts>27.831653</Volts>
                <Amps>4.066727</Amps>
            </Point>
            <Point>
                <Volts>28.072800</Volts>
                <Amps>4.067334</Amps>
            </Point>
            <Point>
                <Volts>28.321170</Volts>
                <Amps>4.067820</Amps>
            </Point>
            <Point>
                <Volts>28.570859</Volts>
                <Amps>4.067213</Amps>
            </Point>
            <Point>
                <Volts>28.813977</Volts>
                <Amps>4.067698</Amps>
            </Point>
            <Point>
                <Volts>29.062350</Volts>
                <Amps>4.066484</Amps>
            </Point>
            <Point>
                <Volts>29.308096</Volts>
                <Amps>4.066727</Amps>
            </Point>
            <Point>
                <Volts>29.558441</Volts>
                <Amps>4.066484</Amps>
            </Point>
            <Point>
                <Volts>29.802872</Volts>
                <Amps>4.065392</Amps>
            </Point>
            <Point>
                <Volts>30.047958</Volts>
                <Amps>4.065270</Amps>
            </Point>
            <Point>
                <Volts>30.290421</Volts>
                <Amps>4.064784</Amps>
            </Point>
            <Point>
                <Volts>30.544708</Volts>
                <Amps>4.064177</Amps>
            </Point>
            <Point>
                <Volts>30.792422</Volts>
                <Amps>4.065149</Amps>
            </Point>
            <Point>
                <Volts>31.033569</Volts>
                <Amps>4.065634</Amps>
            </Point>
            <Point>
                <Volts>31.285229</Volts>
                <Amps>4.063813</Amps>
            </Point>
            <Point>
                <Volts>31.531631</Volts>
                <Amps>4.064420</Amps>
            </Point>
            <Point>
                <Volts>31.776721</Volts>
                <Amps>4.063691</Amps>
            </Point>
            <Point>
                <Volts>32.026410</Volts>
                <Amps>4.063449</Amps>
            </Point>
            <Point>
                <Volts>32.273465</Volts>
                <Amps>4.063084</Amps>
            </Point>
            <Point>
                <Volts>32.515927</Volts>
                <Amps>4.063691</Amps>
            </Point>
            <Point>
                <Volts>32.761673</Volts>
                <Amps>4.063206</Amps>
            </Point>
            <Point>
                <Volts>33.013824</Volts>
                <Amps>4.062204</Amps>
            </Point>
            <Point>
                <Volts>33.256448</Volts>
                <Amps>4.062598</Amps>
            </Point>
            <Point>
                <Volts>33.503510</Volts>
                <Amps>4.061020</Amps>
            </Point>
            <Point>
                <Volts>33.749252</Volts>
                <Amps>4.061384</Amps>
            </Point>
            <Point>
                <Volts>33.998285</Volts>
                <Amps>4.061020</Amps>
            </Point>
            <Point>
                <Volts>34.244687</Volts>
                <Amps>4.061263</Amps>
            </Point>
            <Point>
                <Volts>34.493060</Volts>
                <Amps>4.061141</Amps>
            </Point>
            <Point>
                <Volts>34.738150</Volts>
                <Amps>4.060898</Amps>
            </Point>
            <Point>
                <Volts>34.985867</Volts>
                <Amps>4.060656</Amps>
            </Point>
            <Point>
                <Volts>35.232266</Volts>
                <Amps>4.059198</Amps>
            </Point>
            <Point>
                <Volts>35.476041</Volts>
                <Amps>4.060534</Amps>
            </Point>
            <Point>
                <Volts>35.728360</Volts>
                <Amps>4.059806</Amps>
            </Point>
            <Point>
                <Volts>35.970163</Volts>
                <Amps>4.058105</Amps>
            </Point>
            <Point>
                <Volts>36.214594</Volts>
                <Amps>4.058348</Amps>
            </Point>
            <Point>
                <Volts>36.464938</Volts>
                <Amps>4.058470</Amps>
            </Point>
            <Point>
                <Volts>36.710025</Volts>
                <Amps>4.057498</Amps>
            </Point>
            <Point>
                <Volts>36.957742</Volts>
                <Amps>4.057134</Amps>
            </Point>
            <Point>
                <Volts>37.202829</Volts>
                <Amps>4.055798</Amps>
            </Point>
            <Point>
                <Volts>37.454489</Volts>
                <Amps>4.055920</Amps>
            </Point>
            <Point>
                <Volts>37.701547</Volts>
                <Amps>4.055191</Amps>
            </Point>
            <Point>
                <Volts>37.941382</Volts>
                <Amps>4.054706</Amps>
            </Point>
            <Point>
                <Volts>38.185812</Volts>
                <Amps>4.048149</Amps>
            </Point>
            <Point>
                <Volts>38.426300</Volts>
                <Amps>4.021434</Amps>
            </Point>
            <Point>
                <Volts>38.652335</Volts>
                <Amps>3.986099</Amps>
            </Point>
            <Point>
                <Volts>38.884940</Volts>
                <Amps>3.943478</Amps>
            </Point>
            <Point>
                <Volts>39.111627</Volts>
                <Amps>3.893450</Amps>
            </Point>
            <Point>
                <Volts>39.331747</Volts>
                <Amps>3.839658</Amps>
            </Point>
            <Point>
                <Volts>39.557123</Volts>
                <Amps>3.779430</Amps>
            </Point>
            <Point>
                <Volts>39.776752</Volts>
                <Amps>3.712948</Amps>
            </Point>
            <Point>
                <Volts>39.994080</Volts>
                <Amps>3.641124</Amps>
            </Point>
            <Point>
                <Volts>40.206314</Volts>
                <Amps>3.562924</Amps>
            </Point>
            <Point>
                <Volts>40.415918</Volts>
                <Amps>3.478775</Amps>
            </Point>
            <Point>
                <Volts>40.630780</Volts>
                <Amps>3.389648</Amps>
            </Point>
            <Point>
                <Volts>40.833160</Volts>
                <Amps>3.294570</Amps>
            </Point>
            <Point>
                <Volts>41.037512</Volts>
                <Amps>3.193178</Amps>
            </Point>
            <Point>
                <Volts>41.243173</Volts>
                <Amps>3.085229</Amps>
            </Point>
            <Point>
                <Volts>41.439636</Volts>
                <Amps>2.969994</Amps>
            </Point>
            <Point>
                <Volts>41.637421</Volts>
                <Amps>2.849538</Amps>
            </Point>
            <Point>
                <Volts>41.833881</Volts>
                <Amps>2.721675</Amps>
            </Point>
            <Point>
                <Volts>42.028375</Volts>
                <Amps>2.586405</Amps>
            </Point>
            <Point>
                <Volts>42.214331</Volts>
                <Amps>2.446763</Amps>
            </Point>
            <Point>
                <Volts>42.404880</Volts>
                <Amps>2.303115</Amps>
            </Point>
            <Point>
                <Volts>42.582947</Volts>
                <Amps>2.150116</Amps>
            </Point>
            <Point>
                <Volts>42.762985</Volts>
                <Amps>1.991289</Amps>
            </Point>
            <Point>
                <Volts>42.939737</Volts>
                <Amps>1.827362</Amps>
            </Point>
            <Point>
                <Volts>43.123715</Volts>
                <Amps>1.659792</Amps>
            </Point>
            <Point>
                <Volts>43.291931</Volts>
                <Amps>1.483965</Amps>
            </Point>
            <Point>
                <Volts>43.468024</Volts>
                <Amps>1.303888</Amps>
            </Point>
            <Point>
                <Volts>43.632950</Volts>
                <Amps>1.118225</Amps>
            </Point>
            <Point>
                <Volts>43.803131</Volts>
                <Amps>0.928920</Amps>
            </Point>
            <Point>
                <Volts>43.971341</Volts>
                <Amps>0.732572</Amps>
            </Point>
            <Point>
                <Volts>44.136264</Volts>
                <Amps>0.533431</Amps>
            </Point>
            <Point>
                <Volts>44.297250</Volts>
                <Amps>0.326761</Amps>
            </Point>
            <Point>
                <Volts>44.453632</Volts>
                <Amps>0.119485</Amps>
            </Point>
            <Point>
                <Volts>44.539053</Volts>
                <Amps>0.011657</Amps>
            </Point>
            <Point>
                <Volts>44.539053</Volts>
                <Amps>0.011778</Amps>
            </Point>
            <Point>
                <Volts>44.542337</Volts>
                <Amps>0.012386</Amps>
            </Point>
            <Point>
                <Volts>44.542996</Volts>
                <Amps>0.011657</Amps>
            </Point>
            <Point>
                <Volts>44.536425</Volts>
                <Amps>0.000000</Amps>
            </Point>
        </Points>
    </Curve>
</IV_Curves>
